jsub/VERSION
jsub/__init__.py
jsub/error.py
jsub/loader.py
jsub/log.py
jsub/task.py
jsub/util.py
jsub/command/__init__.py
jsub/command/create.py
jsub/command/ls.py
jsub/command/run.py
jsub/command/show.py
jsub/command/submit.py
jsub/config/__init__.py
jsub/config/error.py
jsub/config/json_config.py
jsub/config/py_config.py
jsub/config/toml_config.py
jsub/config/update.py
jsub/config/yaml_config.py
jsub/config/yml_config.py
jsub/config/handler/__init__.py
jsub/config/handler/json_config.py
jsub/config/handler/py_config.py
jsub/config/handler/toml_config.py
jsub/config/handler/yaml_config.py
jsub/config/handler/yml_config.py
jsub/exts/__init__.py
jsub/exts/config.yml
jsub/exts/action/cmd/cmd.sh
jsub/exts/action/cmd/param.yml
jsub/exts/action/exe/exe.sh
jsub/exts/action/exe/param.yml
jsub/exts/app/__init__.py
jsub/exts/app/common.py
jsub/exts/app/simple.py
jsub/exts/aux/__init__.py
jsub/exts/aux/dirac_task.py
jsub/exts/backend/__init__.py
jsub/exts/backend/local/__init__.py
jsub/exts/bootstrap/shell/bootstrap.sh
jsub/exts/bootstrap/shell/param.yml
jsub/exts/content/__init__.py
jsub/exts/content/file_system.py
jsub/exts/launcher/arg/launcher.sh
jsub/exts/launcher/arg/param.yml
jsub/exts/navigator/hehe/navigator
jsub/exts/navigator/hehe/param.yml
jsub/exts/navigator/python/nav.py
jsub/exts/navigator/python/param.yml
jsub/exts/navigator/xixi/navigator
jsub/exts/repo/__init__.py
jsub/exts/repo/file_system.py
jsub/exts/splitter/__init__.py
jsub/exts/splitter/custom_iter.py
jsub/exts/splitter/sequence.py
jsub/manager/__init__.py
jsub/manager/action.py
jsub/manager/app.py
jsub/manager/backend.py
jsub/manager/bootstrap.py
jsub/manager/config.py
jsub/manager/error.py
jsub/manager/extension.py
jsub/manager/launcher.py
jsub/manager/navigator.py
jsub/manager/scenario.py
jsub/manager/splitter.py
jsub/mixin/__init__.py
jsub/mixin/backend/__init__.py
jsub/mixin/backend/common.py
jsub/operation/__init__.py
jsub-0.1.0.dev2.dist-info/DESCRIPTION.rst
jsub-0.1.0.dev2.dist-info/METADATA
jsub-0.1.0.dev2.dist-info/RECORD
jsub-0.1.0.dev2.dist-info/WHEEL
jsub-0.1.0.dev2.dist-info/entry_points.txt
jsub-0.1.0.dev2.dist-info/metadata.json
jsub-0.1.0.dev2.dist-info/top_level.txt
